sem_search_fast/__init__.py
sem_search_fast/utils.py
sem_search_fast-0.0.3.dist-info/LICENSE
sem_search_fast-0.0.3.dist-info/METADATA
sem_search_fast-0.0.3.dist-info/WHEEL
sem_search_fast-0.0.3.dist-info/top_level.txt
sem_search_fast-0.0.3.dist-info/RECORD
