Metadata-Version: 2.1
Name: sem-search-fast
Version: 0.0.3
Summary: For quick semantic search
Home-page: https://github.com/philfvbell/sem_search_fast
Author: Phil Bell
Author-email: philipfvbell@gmail.com
Classifier: Programming Language :: Python :: 3
Classifier: License :: OSI Approved :: MIT License
Classifier: Operating System :: OS Independent
Requires-Python: >=3.7
License-File: LICENSE
